routerhk/__init__.py
routerhk/routerhk.py
routerhk-250715.dist-info/LICENSE
routerhk-250715.dist-info/METADATA
routerhk-250715.dist-info/WHEEL
routerhk-250715.dist-info/top_level.txt
routerhk-250715.dist-info/RECORD
