Metadata-Version: 2.2
Name: routerhk
Version: 250715
Summary: API client for router.hk API requests.
Home-page: https://github.com/routerhk/routerhk
Author: Sammy Fung
Author-email: sammy@sammy.hk
Classifier: Programming Language :: Python :: 3
Classifier: License :: OSI Approved :: Apache Software License
Classifier: Operating System :: OS Independent
Requires-Python: >=3.6
License-File: LICENSE
Requires-Dist: requests
Dynamic: author
Dynamic: author-email
Dynamic: classifier
Dynamic: home-page
Dynamic: requires-dist
Dynamic: requires-python
Dynamic: summary
